<?xml version="1.0" encoding="UTF-8"?>

<mule xmlns:blackboard="http://www.mulesoft.org/schema/connectivity/blackboard"
	xmlns:http="http://www.mulesoft.org/schema/mule/http"
	xmlns:ee="http://www.mulesoft.org/schema/mule/ee/core" xmlns="http://www.mulesoft.org/schema/mule/core"
	xmlns:doc="http://www.mulesoft.org/schema/mule/documentation"
	xmlns:xsi="http://www.w3.org/2001/XMLSchema-instance" xsi:schemaLocation="
http://www.mulesoft.org/schema/mule/http http://www.mulesoft.org/schema/mule/http/current/mule-http.xsd 
http://www.mulesoft.org/schema/mule/ee/core http://www.mulesoft.org/schema/mule/ee/core/current/mule-ee.xsd http://www.mulesoft.org/schema/mule/core http://www.mulesoft.org/schema/mule/core/current/mule.xsd
http://www.mulesoft.org/schema/connectivity/blackboard http://www.mulesoft.org/schema/connectivity/blackboard/current/mule-blackboard.xsd">
	<flow name="put:\v1\catalog\categories\(categoryType)\(categoryId)\courses\(courseId):blackboard-rest-api-config">
        <http:listener doc:name="Listener" doc:id="e36477c6-bf42-4e4c-95a1-b1493bf1cfe9" config-ref="HTTP_Listener_config" allowedMethods="PUT" path="/v1/catalog/categories/{categoryType}\{categoryId}\courses\{courseId}">
			<http:response statusCode="#[vars.httpStatus default 200]" />
			<http:error-response statusCode="#[vars.httpStatus default 500]" >
				<http:body ><![CDATA[#[output application/json --- payload default error.description]]]></http:body>
			</http:error-response>
		</http:listener>
		<ee:transform doc:name="Transform Message">
            <ee:variables>
                <ee:set-variable variableName="categoryType">attributes.uriParams.'categoryType'</ee:set-variable>
                <ee:set-variable variableName="categoryId">attributes.uriParams.'categoryId'</ee:set-variable>
                <ee:set-variable variableName="courseId">attributes.uriParams.'courseId'</ee:set-variable>
            </ee:variables>
        </ee:transform>
        <flow-ref doc:name="blackboard-token-subFlow" doc:id="ab42ecf9-122d-47c9-806f-aa67b0dda9ae" name="accesstoken_Flow" target="blackboardToken"/>
		<blackboard:create-category-membership doc:name="Course Category - Create Category Membership" doc:id="d15fc4be-5ffa-4b0e-ae5a-2913b94c9f79" categoryType="#[vars.categoryType]" categoryId="#[vars.categoryId]" courseId="#[vars.courseId]" correlationId="#[correlationId]" config-ref="Blackboard_config"/>
		<set-variable value="#[attributes.statusCode]" doc:name="httpStatus" doc:id="7fa6de9f-ee8b-44f7-979e-7c976263e3fe" variableName="httpStatus" />
    </flow>
    <flow name="put:\v1\courses\(courseId)\children\(childCourseId):blackboard-rest-api-config">
        <http:listener doc:name="Listener" doc:id="a81f6ad6-08c0-46f2-a12d-ac7f9c6352e4" config-ref="HTTP_Listener_config" path="/v1/courses/{courseId}/children/{childCourseId}" allowedMethods="PUT" >
			<http:response statusCode="#[vars.httpStatus default 200]" />
			<http:error-response statusCode="#[vars.httpStatus default 500]" >
				<http:body ><![CDATA[#[output application/json --- payload default error.description]]]></http:body>
			</http:error-response>
		</http:listener>
		<ee:transform doc:name="Transform Message">
            <ee:variables>
                <ee:set-variable variableName="courseId">attributes.uriParams.'courseId'</ee:set-variable>
                <ee:set-variable variableName="childCourseId">attributes.uriParams.'childCourseId'</ee:set-variable>
            </ee:variables>
        </ee:transform>
        <flow-ref doc:name="blackboard-token-subFlow" doc:id="cb9415b7-8e3a-4a8b-8e1e-735d3cc07f81" name="accesstoken_Flow" target="blackboardToken"/>
		<blackboard:add-child-course doc:name="Courses - Add Child Course" doc:id="21e553b3-9233-4763-85fb-a1a61b693a69" config-ref="Blackboard_config" courseId="#[vars.courseId]" childCourseId="#[vars.childCourseId]" correlationId="#[correlationId]"/>
    </flow>
    <flow name="put:\v1\courses\(courseId)\users\(userId):application\json:blackboard-rest-api-config">
        <http:listener doc:name="Listener" doc:id="077041a8-53a2-4818-b80d-44a3d1bf8cf3" config-ref="HTTP_Listener_config" path="/v1/courses/{courseId}/users/{userId}" allowedMethods="PUT" >
			<http:response statusCode="#[vars.httpStatus default 200]" />
			<http:error-response statusCode="#[vars.httpStatus default 500]" >
				<http:body ><![CDATA[#[output application/json --- payload default error.description]]]></http:body>
			</http:error-response>
		</http:listener>
		<ee:transform doc:name="Transform Message">
            <ee:variables>
                <ee:set-variable variableName="courseId">attributes.uriParams.'courseId'</ee:set-variable>
                <ee:set-variable variableName="userId">attributes.uriParams.'userId'</ee:set-variable>
            </ee:variables>
        </ee:transform>
        <flow-ref doc:name="blackboard-token-subFlow" doc:id="860bc272-429a-458e-af00-8ade30e12dcb" name="accesstoken_Flow" target="blackboardToken"/>
		<blackboard:create-course-user-membership doc:name="Course Membership - Create Course User Membership" doc:id="c70eae45-69ca-41d5-bbcc-c24373b02564" config-ref="Blackboard_config" courseId="#[vars.courseId]" userId="#[vars.userId]" correlationId="#[correlationId]">
			<blackboard:course_membership_-_create_course_user_membership--body ><![CDATA[#[payload]]]></blackboard:course_membership_-_create_course_user_membership--body>
		</blackboard:create-course-user-membership>
    </flow>
    <flow name="delete:\v1\catalog\categories\(categoryType)\(categoryId):blackboard-rest-api-config">
        <http:listener doc:name="Listener" doc:id="9e882060-4c83-498c-8069-3a3cb262fad3" config-ref="HTTP_Listener_config" path="/v1/catalog/categories/{categoryType}/{categoryId}" allowedMethods="DELETE" >
			<http:response statusCode="#[vars.httpStatus default 200]" />
			<http:error-response statusCode="#[vars.httpStatus default 500]" >
				<http:body ><![CDATA[#[output application/json --- payload default error.description]]]></http:body>
			</http:error-response>
		</http:listener>
		<ee:transform doc:name="Transform Message">
            <ee:variables>
                <ee:set-variable variableName="categoryType">attributes.uriParams.'categoryType'</ee:set-variable>
                <ee:set-variable variableName="categoryId">attributes.uriParams.'categoryId'</ee:set-variable>
            </ee:variables>
        </ee:transform>
        <flow-ref doc:name="blackboard-token-subFlow" doc:id="72483487-01e3-474d-905d-153d743b4416" name="accesstoken_Flow" target="blackboardToken"/>
		<blackboard:delete-category doc:name="Course Category - Delete Category" doc:id="f9ac0aab-b26d-4e1d-9bea-38366f5e0f29" config-ref="Blackboard_config" categoryType="#[vars.categoryType]" categoryId="#[vars.categoryId]" correlationId="#[correlationId]"/>
    </flow>
    <flow name="delete:\v1\catalog\categories\(categoryType)\(categoryId)\courses\(courseId):blackboard-rest-api-config">
        <http:listener doc:name="Listener" doc:id="2fc5d451-112b-4e62-8857-47aefcac0267" config-ref="HTTP_Listener_config" path="/v1/catalog/categories/{categoryType}/{categoryId}/courses/{courseId}" allowedMethods="DELETE" >
			<http:response statusCode="#[vars.httpStatus default 200]" />
			<http:error-response statusCode="#[vars.httpStatus default 500]" >
				<http:body ><![CDATA[#[output application/json --- payload default error.description]]]></http:body>
			</http:error-response>
		</http:listener>
		<ee:transform doc:name="Transform Message">
            <ee:variables>
                <ee:set-variable variableName="categoryType">attributes.uriParams.'categoryType'</ee:set-variable>
                <ee:set-variable variableName="categoryId">attributes.uriParams.'categoryId'</ee:set-variable>
                <ee:set-variable variableName="courseId">attributes.uriParams.'courseId'</ee:set-variable>
            </ee:variables>
        </ee:transform>
        <flow-ref doc:name="blackboard-token-subFlow" doc:id="9cc0434b-7096-47ce-89f1-069e9795427a" name="accesstoken_Flow" target="blackboardToken"/>
		<blackboard:delete-category-membership doc:name="Course Category - Delete Category Membership" doc:id="0394f037-db57-4504-a707-83bf2b45a2f3" config-ref="Blackboard_config" categoryType="#[vars.categoryType]" categoryId="#[vars.categoryId]" courseId="#[vars.courseId]" correlationId="#[correlationId]"/>
    </flow>
    <flow name="delete:\v1\courses\(courseId)\children\(childCourseId):blackboard-rest-api-config">
        <http:listener doc:name="Listener" doc:id="d4a63d99-eb69-4dda-9ea3-842dfbdde919" config-ref="HTTP_Listener_config" path="/v1/courses/{courseId}/children/{childCourseId}" allowedMethods="DELETE" >
			<http:response statusCode="#[vars.httpStatus default 200]" />
			<http:error-response statusCode="#[vars.httpStatus default 500]" >
				<http:body ><![CDATA[#[output application/json --- payload default error.description]]]></http:body>
			</http:error-response>
		</http:listener>
		<ee:transform doc:name="Transform Message">
            <ee:variables>
                <ee:set-variable variableName="courseId">attributes.uriParams.'courseId'</ee:set-variable>
                <ee:set-variable variableName="childCourseId">attributes.uriParams.'childCourseId'</ee:set-variable>
            </ee:variables>
        </ee:transform>
        <flow-ref doc:name="blackboard-token-subFlow" doc:id="2b2814f4-5e4a-4ec7-b065-d65c05c7bd55" name="accesstoken_Flow" target="blackboardToken"/>
		<blackboard:remove-child-course doc:name="Courses - Remove Child Course" doc:id="3bbc74a4-4b1c-41b5-aeb5-88da85ce24f1" config-ref="Blackboard_config" courseId="#[vars.courseId]" childCourseId="#[vars.childCourseId]" correlationId="#[correlationId]"/>
    </flow>
    <flow name="delete:\v1\courses\(courseId)\meetings:blackboard-rest-api-config">
        <http:listener doc:name="Listener" doc:id="2f7f6fc8-7640-4868-8e51-90b2c2d46aeb" config-ref="HTTP_Listener_config" path="/v1/courses/{courseId}/meetings" allowedMethods="DELETE" >
			<http:response statusCode="#[vars.httpStatus default 200]" />
			<http:error-response statusCode="#[vars.httpStatus default 500]" >
				<http:body ><![CDATA[#[output application/json --- payload default error.description]]]></http:body>
			</http:error-response>
		</http:listener>
		<ee:transform doc:name="Transform Message">
            <ee:variables>
                <ee:set-variable variableName="courseId">attributes.uriParams.'courseId'</ee:set-variable>
            </ee:variables>
        </ee:transform>
        <flow-ref doc:name="blackboard-token-subFlow" doc:id="e6dda236-73ee-499d-9194-391290dc6dce" name="accesstoken_Flow" target="blackboardToken"/>
		<blackboard:delete-course-meeting doc:name="Attendance - Delete Course Meeting" doc:id="29e3893d-1561-4af4-a67a-f06a0075881c" config-ref="Blackboard_config" courseId="#[vars.courseId]" correlationId="#[correlationId]"/>
    </flow>
    <flow name="delete:\v1\courses\(courseId)\meetings\users\(userId):blackboard-rest-api-config">
        <http:listener doc:name="Listener" doc:id="3765b02f-8a8b-42c2-910f-276ec0194ab8" config-ref="HTTP_Listener_config" path="/v1/courses/{courseId}/meetings/users/{userId}" allowedMethods="DELETE" >
			<http:response statusCode="#[vars.httpStatus default 200]" />
			<http:error-response statusCode="#[vars.httpStatus default 500]" >
				<http:body ><![CDATA[#[output application/json --- payload default error.description]]]></http:body>
			</http:error-response>
		</http:listener>
		<ee:transform doc:name="Transform Message">
            <ee:variables>
                <ee:set-variable variableName="courseId">attributes.uriParams.'courseId'</ee:set-variable>
                <ee:set-variable variableName="userId">attributes.uriParams.'userId'</ee:set-variable>
            </ee:variables>
        </ee:transform>
        <flow-ref doc:name="blackboard-token-subFlow" doc:id="8cad5a8b-b914-4427-bd9b-6976ed96f024" name="accesstoken_Flow" target="blackboardToken"/>
		<blackboard:delete-all-attendance-records-by-courseand-user-id doc:name="Attendance - Delete All Attendance Records by Course and User Id" doc:id="fc0f7105-f833-49c5-9dc4-768fd650bb8f" config-ref="Blackboard_config" courseId="#[vars.courseId]" userId="#[vars.userId]" correlationId="#[correlationId]"/>
    </flow>
    <flow name="delete:\v1\courses\(courseId)\meetings\(meetingId)\users\(userId):blackboard-rest-api-config">
        <http:listener doc:name="Listener" doc:id="443c2f53-9acf-48fb-9b7f-4e704eab492f" config-ref="HTTP_Listener_config" path="/v1/courses/{courseId}/meetings/{meetingId}/users/{userId}" allowedMethods="DELETE" >
			<http:response statusCode="#[vars.httpStatus default 200]" />
			<http:error-response statusCode="#[vars.httpStatus default 500]" >
				<http:body ><![CDATA[#[output application/json --- payload default error.description]]]></http:body>
			</http:error-response>
		</http:listener>
		<ee:transform doc:name="Transform Message">
            <ee:variables>
                <ee:set-variable variableName="courseId">attributes.uriParams.'courseId'</ee:set-variable>
                <ee:set-variable variableName="meetingId">attributes.uriParams.'meetingId'</ee:set-variable>
                <ee:set-variable variableName="userId">attributes.uriParams.'userId'</ee:set-variable>
            </ee:variables>
        </ee:transform>
        <flow-ref doc:name="blackboard-token-subFlow" doc:id="cd362246-ad67-4c03-a868-52ccf3d3f395" name="accesstoken_Flow" target="blackboardToken"/>
		<blackboard:delete-attendance-record doc:name="Attendance - Delete Attendance Record" doc:id="2b2d0751-e0f8-479b-9579-cdbdce4f6efb" config-ref="Blackboard_config" courseId="#[vars.courseId]" meetingId="#[vars.meetingId]" userId="#[vars.userId]" correlationId="#[correlationId]"/>
    </flow>
    <flow name="delete:\v1\courses\(courseId)\users\(userId):blackboard-rest-api-config">
        <http:listener doc:name="Listener" doc:id="a12708d9-0cf6-4ef6-9d1c-e498fac8e5dc" config-ref="HTTP_Listener_config" path="/v1/courses/{courseId}/users/{userId}" allowedMethods="DELETE" >
			<http:response statusCode="#[vars.httpStatus default 200]" />
			<http:error-response statusCode="#[vars.httpStatus default 500]" >
				<http:body ><![CDATA[#[output application/json --- payload default error.description]]]></http:body>
			</http:error-response>
		</http:listener>
		<ee:transform doc:name="Transform Message">
            <ee:variables>
                <ee:set-variable variableName="courseId">attributes.uriParams.'courseId'</ee:set-variable>
                <ee:set-variable variableName="userId">attributes.uriParams.'userId'</ee:set-variable>
            </ee:variables>
        </ee:transform>
        <flow-ref doc:name="blackboard-token-subFlow" doc:id="c436eb40-6d15-4203-a4bc-b99ceb72f146" name="accesstoken_Flow" target="blackboardToken"/>
		<blackboard:delete-course-membership doc:name="Course Membership - Delete Course Membership" doc:id="2a7855a5-54ea-43c4-b14f-31154d5328cd" config-ref="Blackboard_config" courseId="#[vars.courseId]" userId="#[vars.userId]" correlationId="#[correlationId]"/>
    </flow>
    <flow name="delete:\v1\terms\(termId):blackboard-rest-api-config">
        <http:listener doc:name="Listener" doc:id="c73c7b88-7e2e-41b9-b5ef-127d6ca7eb17" config-ref="HTTP_Listener_config" path="/v1/terms/{termId}" allowedMethods="DELETE" >
			<http:response statusCode="#[vars.httpStatus default 200]" />
			<http:error-response statusCode="#[vars.httpStatus default 500]" >
				<http:body ><![CDATA[#[output application/json --- payload default error.description]]]></http:body>
			</http:error-response>
		</http:listener>
		<ee:transform doc:name="Transform Message">
            <ee:variables>
                <ee:set-variable variableName="termId">attributes.uriParams.'termId'</ee:set-variable>
            </ee:variables>
        </ee:transform>
        <flow-ref doc:name="blackboard-token-subFlow" doc:id="75e20c55-27bd-45da-99a8-aef74e67becf" name="accesstoken_Flow" target="blackboardToken"/>
		<blackboard:delete-term doc:name="Terms - Delete Term" doc:id="281d6a3a-894c-4478-b477-3c02d916d4ec" config-ref="Blackboard_config" termId="#[vars.termId]" correlationId="#[correlationId]"/>
    </flow>
    <flow name="delete:\v1\users\(userId):blackboard-rest-api-config">
        <http:listener doc:name="Listener" doc:id="fa82d91d-1394-42e4-a176-e7257657447b" config-ref="HTTP_Listener_config" path="/v1/users/{userId}" allowedMethods="DELETE" >
			<http:response statusCode="#[vars.httpStatus default 200]" />
			<http:error-response statusCode="#[vars.httpStatus default 500]" >
				<http:body ><![CDATA[#[output application/json --- payload default error.description]]]></http:body>
			</http:error-response>
		</http:listener>
		<ee:transform doc:name="Transform Message">
            <ee:variables>
                <ee:set-variable variableName="userId">attributes.uriParams.'userId'</ee:set-variable>
            </ee:variables>
        </ee:transform>
        <flow-ref doc:name="blackboard-token-subFlow" doc:id="73ba15ff-0263-45e9-973f-b34d35203375" name="accesstoken_Flow" target="blackboardToken"/>
        <blackboard:delete-user doc:name="Users - Delete User" doc:id="8e35be98-a783-4017-8930-2e5d5bf91d40" config-ref="Blackboard_config" userId="#[vars.userId]" correlationId="#[correlationId]"/>
		<set-variable value="#[attributes.statusCode]" doc:name="httpStatus" doc:id="6ab8e977-1e5b-4354-94e5-425beaef5ef3" variableName="httpStatus" />
    </flow>
    <flow name="delete:\v3\courses\(courseId):blackboard-rest-api-config">
        <http:listener doc:name="Listener" doc:id="279a1d79-d76a-4030-b5db-d47584e5c697" config-ref="HTTP_Listener_config" path="/v3/courses/{courseId}" allowedMethods="DELETE" >
			<http:response statusCode="#[vars.httpStatus default 200]" />
			<http:error-response statusCode="#[vars.httpStatus default 500]" >
				<http:body ><![CDATA[#[output application/json --- payload default error.description]]]></http:body>
			</http:error-response>
		</http:listener>
		<ee:transform doc:name="Transform Message">
            <ee:variables>
                <ee:set-variable variableName="courseId">attributes.uriParams.'courseId'</ee:set-variable>
            </ee:variables>
        </ee:transform>
        <flow-ref doc:name="blackboard-token-subFlow" doc:id="ca1031b1-c8bc-4c76-83ea-c8c3bcbf5fd8" name="accesstoken_Flow" target="blackboardToken"/>
        <blackboard:delete-course doc:name="Courses - Delete Course" doc:id="4e1fc54a-f453-4566-860b-e524f90ccfc6" config-ref="Blackboard_config" courseId="#[vars.courseId]" correlationId="#[correlationId]"/>
		<set-variable value="#[attributes.statusCode]" doc:name="httpStatus" doc:id="fc108643-0210-40b1-9548-24a7932c30c9" variableName="httpStatus" />
    </flow>
    <flow name="patch:\v1\catalog\categories\(categoryType)\(categoryId):application\json:blackboard-rest-api-config">
        <http:listener doc:name="Listener" doc:id="0b2b0518-52b1-41ee-ab1c-b0a0826e5cd8" config-ref="HTTP_Listener_config" path="/v1/catalog/categories/{categoryType}/{categoryId}" allowedMethods="PATCH" >
			<http:response statusCode="#[vars.httpStatus default 200]" />
			<http:error-response statusCode="#[vars.httpStatus default 500]" >
				<http:body ><![CDATA[#[output application/json --- payload default error.description]]]></http:body>
			</http:error-response>
		</http:listener>
		<ee:transform doc:name="Transform Message">
            <ee:variables>
                <ee:set-variable variableName="categoryType">attributes.uriParams.'categoryType'</ee:set-variable>
                <ee:set-variable variableName="categoryId">attributes.uriParams.'categoryId'</ee:set-variable>
            </ee:variables>
        </ee:transform>
        <blackboard:update-category doc:name="Course Category - Update Category" doc:id="ffbbafe5-dfb8-422b-a01a-7ebe52e12f29" config-ref="Blackboard_config" categoryType="#[vars.categoryType]" categoryId="#[vars.categoryId]" correlationId="#[correlationId]">
			<blackboard:course_category_-_update_category--body ><![CDATA[#[payload]]]></blackboard:course_category_-_update_category--body>
		</blackboard:update-category>
		<flow-ref doc:name="blackboard-token-subFlow" doc:id="4cdfaa0c-6e1f-44f3-afcd-e72d63731932" name="accesstoken_Flow" target="blackboardToken"/>
    </flow>
    <flow name="patch:\v1\courses\(courseId)\meetings\(meetingId)\users\(userId):application\json:blackboard-rest-api-config">
        <http:listener doc:name="Listener" doc:id="d7f0c05d-4660-4c67-9e3b-f07a18b631fe" config-ref="HTTP_Listener_config" path="/v1/courses/{courseId}/meetings/{meetingId}/users/{userId}" allowedMethods="PATCH" >
			<http:response statusCode="#[vars.httpStatus default 200]" />
			<http:error-response statusCode="#[vars.httpStatus default 500]" >
				<http:body ><![CDATA[#[output application/json --- payload default error.description]]]></http:body>
			</http:error-response>
		</http:listener>
		<ee:transform doc:name="Transform Message">
            <ee:variables>
                <ee:set-variable variableName="courseId">attributes.uriParams.'courseId'</ee:set-variable>
                <ee:set-variable variableName="meetingId">attributes.uriParams.'meetingId'</ee:set-variable>
                <ee:set-variable variableName="userId">attributes.uriParams.'userId'</ee:set-variable>
            </ee:variables>
        </ee:transform>
        <flow-ref doc:name="blackboard-token-subFlow" doc:id="43130bd3-1bb4-4869-b449-9504cb3fdfcf" name="accesstoken_Flow" target="blackboardToken"/>
		<blackboard:update-attendance-record doc:name="Attendance - Update Attendance Record" doc:id="b88e1d40-f239-478a-8bf4-5b5a9edee68f" config-ref="Blackboard_config" courseId="#[vars.courseId]" meetingId="#[vars.meetingId]" userId="#[vars.userId]" correlationId="#[correlationId]">
			<blackboard:attendance_-_update_attendance_record--body ><![CDATA[#[payload]]]></blackboard:attendance_-_update_attendance_record--body>
		</blackboard:update-attendance-record>
    </flow>
    <flow name="patch:\v1\courses\(courseId)\users\(userId):application\json:blackboard-rest-api-config">
        <http:listener doc:name="Listener" doc:id="1465e5ee-dbda-4220-8cd0-199afb7f47e5" config-ref="HTTP_Listener_config" path="/v1/courses/{courseId}/users/{userId}" allowedMethods="PATCH" >
			<http:response statusCode="#[vars.httpStatus default 200]" />
			<http:error-response statusCode="#[vars.httpStatus default 500]" >
				<http:body ><![CDATA[#[output application/json --- payload default error.description]]]></http:body>
			</http:error-response>
		</http:listener>
		<ee:transform doc:name="Transform Message">
            <ee:variables>
                <ee:set-variable variableName="courseId">attributes.uriParams.'courseId'</ee:set-variable>
                <ee:set-variable variableName="userId">attributes.uriParams.'userId'</ee:set-variable>
            </ee:variables>
        </ee:transform>
        <flow-ref doc:name="blackboard-token-subFlow" doc:id="cdd1c155-8e21-42c0-99b5-12405e7795cd" name="accesstoken_Flow" target="blackboardToken"/>
		<blackboard:update-course-user-membership doc:name="Course Membership - Update Course User Membership" doc:id="f4bf651d-1995-4a46-af6f-27df720f3dde" config-ref="Blackboard_config" courseId="#[vars.courseId]" userId="#[vars.userId]" correlationId="#[correlationId]">
			<blackboard:course_membership_-_update_course_user_membership--body ><![CDATA[#[payload]]]></blackboard:course_membership_-_update_course_user_membership--body>
		</blackboard:update-course-user-membership>
    </flow>
    <flow name="patch:\v1\terms\(termId):application\json:blackboard-rest-api-config">
        <http:listener doc:name="Listener" doc:id="adf955e4-b358-4c7d-93e3-6380ab55dd4f" config-ref="HTTP_Listener_config" path="/v1/terms/{termId}" allowedMethods="PATCH" >
			<http:response statusCode="#[vars.httpStatus default 200]" />
			<http:error-response statusCode="#[vars.httpStatus default 500]" >
				<http:body ><![CDATA[#[output application/json --- payload default error.description]]]></http:body>
			</http:error-response>
		</http:listener>
		<ee:transform doc:name="Transform Message">
            <ee:variables>
                <ee:set-variable variableName="termId">attributes.uriParams.'termId'</ee:set-variable>
            </ee:variables>
        </ee:transform>
        <flow-ref doc:name="blackboard-token-subFlow" doc:id="8afb0f2b-5cc1-4b28-ae89-a8840ad66198" name="accesstoken_Flow" target="blackboardToken"/>
		<blackboard:update-term doc:name="Terms - Update Term" doc:id="9d2ccdc1-60b6-4eda-bff2-8c6241b70bec" config-ref="Blackboard_config" termId="#[vars.termId]" correlationId="#[correlationId]">
			<blackboard:terms_-_update_term--body ><![CDATA[#[payload]]]></blackboard:terms_-_update_term--body>
		</blackboard:update-term>
    </flow>
    <flow name="patch:\v1\users\(userId):application\json:blackboard-rest-api-config">
        <http:listener doc:name="Listener" doc:id="4e178b20-fc33-4829-a9e6-d9cf431e6dfb" config-ref="HTTP_Listener_config" path="/v1/users/{userId}" allowedMethods="PATCH" >
			<http:response statusCode="#[vars.httpStatus default 200]" />
			<http:error-response statusCode="#[vars.httpStatus default 500]" >
				<http:body ><![CDATA[#[output application/json --- payload default error.description]]]></http:body>
			</http:error-response>
		</http:listener>
		<ee:transform doc:name="Transform Message">
            <ee:variables>
                <ee:set-variable variableName="userId">attributes.uriParams.'userId'</ee:set-variable>
            </ee:variables>
        </ee:transform>
        <flow-ref doc:name="blackboard-token-subFlow" doc:id="f417b29f-9e02-4699-824e-7750f0a63410" name="accesstoken_Flow" target="blackboardToken"/>
		<blackboard:update-user doc:name="Users - Update User" doc:id="c6c1facf-da08-40d0-948c-ac084f3bbc4d" config-ref="Blackboard_config" userId="#[vars.userId]" correlationId="#[correlationId]">
			<blackboard:users_-_update_user--body ><![CDATA[#[payload]]]></blackboard:users_-_update_user--body>
		</blackboard:update-user>
    </flow>
    <flow name="patch:\v3\courses\(courseId):application\json:blackboard-rest-api-config">
        <http:listener doc:name="Listener" doc:id="e6d3d9cb-720e-4dc8-9025-b3417610907f" config-ref="HTTP_Listener_config" path="/v3/courses/{courseId}" allowedMethods="PATCH" >
			<http:response statusCode="#[vars.httpStatus default 200]" />
			<http:error-response statusCode="#[vars.httpStatus default 500]" >
				<http:body ><![CDATA[#[output application/json --- payload default error.description]]]></http:body>
			</http:error-response>
		</http:listener>
		<ee:transform doc:name="Transform Message">
            <ee:variables>
                <ee:set-variable variableName="courseId">attributes.uriParams.'courseId'</ee:set-variable>
            </ee:variables>
        </ee:transform>
        <flow-ref doc:name="blackboard-token-subFlow" doc:id="a76e71bd-a738-4613-bf8d-91e9e6afe144" name="accesstoken_Flow" target="blackboardToken"/>
		<blackboard:update-course doc:name="Courses - Update Course" doc:id="52863315-7ed5-4645-906d-f419f79f7d2c" config-ref="Blackboard_config" courseId="#[vars.courseId]" correlationId="#[correlationId]">
			<blackboard:courses_-_update_course--body ><![CDATA[#[payload]]]></blackboard:courses_-_update_course--body>
		</blackboard:update-course>
    </flow>
    <flow name="get:\v1\calendars\items:blackboard-rest-api-config">
        <http:listener doc:name="Listener" doc:id="1beadcf8-cd9f-4c44-a8a9-fa5d0dea20eb" config-ref="HTTP_Listener_config" path="/v1/calendars/items" allowedMethods="GET" >
			<http:response statusCode="#[vars.httpStatus default 200]" />
			<http:error-response statusCode="#[vars.httpStatus default 500]" >
				<http:body ><![CDATA[#[output application/json --- payload default error.description]]]></http:body>
			</http:error-response>
		</http:listener>
		<flow-ref doc:name="blackboard-token-subFlow" doc:id="553d5e73-e256-4e31-be30-a77944c8808e" name="accesstoken_Flow" target="blackboardToken"/>
		<blackboard:upcoming-events doc:name="Users - Upcoming events" doc:id="61f3d51a-24e6-4feb-9592-0f6d7d3aab7c" config-ref="Blackboard_config" correlationId="#[correlationId]"/>
    
</flow>
    <flow name="get:\v1\catalog\categories\(categoryType):blackboard-rest-api-config">
        <http:listener doc:name="Listener" doc:id="df534d75-3a6d-42f2-b645-cba43e19c997" config-ref="HTTP_Listener_config" path="/v1/catalog/categories/{categoryType}" allowedMethods="GET" >
			<http:response statusCode="#[vars.httpStatus default 200]" />
			<http:error-response statusCode="#[vars.httpStatus default 500]" >
				<http:body ><![CDATA[#[output application/json --- payload default error.description]]]></http:body>
			</http:error-response>
		</http:listener>
		<ee:transform doc:name="Transform Message">
            <ee:variables>
                <ee:set-variable variableName="categoryType">attributes.uriParams.'categoryType'</ee:set-variable>
            </ee:variables>
        </ee:transform>
        <flow-ref doc:name="blackboard-token-subFlow" doc:id="4d438a0d-9427-48a9-abf5-44a9bd7986f1" name="accesstoken_Flow" target="blackboardToken"/>
		<blackboard:get-categories doc:name="Course Category - Get Categories" doc:id="0626b8b2-7982-4466-a936-8208e3d463fa" config-ref="Blackboard_config" categoryType="#[vars.categoryType]" correlationId="#[correlationId]"/>
    
</flow>
    <flow name="get:\v1\catalog\categories\(categoryType)\(categoryId):blackboard-rest-api-config">
        <http:listener doc:name="Listener" doc:id="71805669-90ca-4de9-b0f2-c18229f465ee" config-ref="HTTP_Listener_config" path="/v1/catalog/categories/{categoryType}/{categoryId}" allowedMethods="GET" >
			<http:response statusCode="#[vars.httpStatus default 200]" />
			<http:error-response statusCode="#[vars.httpStatus default 500]" >
				<http:body ><![CDATA[#[output application/json --- payload default error.description]]]></http:body>
			</http:error-response>
		</http:listener>
		<ee:transform doc:name="Transform Message">
            <ee:variables>
                <ee:set-variable variableName="categoryType">attributes.uriParams.'categoryType'</ee:set-variable>
                <ee:set-variable variableName="categoryId">attributes.uriParams.'categoryId'</ee:set-variable>
            </ee:variables>
        </ee:transform>
        <flow-ref doc:name="blackboard-token-subFlow" doc:id="73a7e717-8cfd-4d7f-bf12-08ef4e74e5c4" name="accesstoken_Flow" target="blackboardToken"/>
		<blackboard:get-category doc:name="Course Category - Get Category" doc:id="9c81fe4c-5286-4f47-9ce1-3cb96736a7dc" config-ref="Blackboard_config" categoryType="#[vars.categoryType]" categoryId="#[vars.categoryId]" correlationId="#[correlationId]"/>
    
</flow>
    <flow name="get:\v1\catalog\categories\(categoryType)\(categoryId)\courses:blackboard-rest-api-config">
        <http:listener doc:name="Listener" doc:id="0afd85d4-860f-4ed6-93e8-7a66bd91098e" config-ref="HTTP_Listener_config" path="/v1/catalog/categories/{categoryType}/{categoryId}/courses" allowedMethods="GET" >
			<http:response statusCode="#[vars.httpStatus default 200]" />
			<http:error-response statusCode="#[vars.httpStatus default 500]" >
				<http:body ><![CDATA[#[output application/json --- payload default error.description]]]></http:body>
			</http:error-response>
		</http:listener>
		<ee:transform doc:name="Transform Message">
            <ee:variables>
                <ee:set-variable variableName="categoryType">attributes.uriParams.'categoryType'</ee:set-variable>
                <ee:set-variable variableName="categoryId">attributes.uriParams.'categoryId'</ee:set-variable>
            </ee:variables>
        </ee:transform>
        <flow-ref doc:name="blackboard-token-subFlow" doc:id="7cff56fb-839f-42d9-a465-4900a6bb5029" name="accesstoken_Flow" target="blackboardToken"/>
		<blackboard:get-category-memberships doc:name="Course Category - Get Category Memberships" doc:id="832bc904-cb19-4784-bb92-e760e153dcd4" config-ref="Blackboard_config" categoryType="#[vars.categoryType]" categoryId="#[vars.categoryId]" correlationId="#[correlationId]"/>
    
</flow>
    <flow name="get:\v1\catalog\categories\(categoryType)\(parentId)\children:blackboard-rest-api-config">
        <http:listener doc:name="Listener" doc:id="7aa6a57f-19a8-444c-a2d1-f4c59fe8d09e" config-ref="HTTP_Listener_config" path="/v1/catalog/categories/{categoryType}/{parentId}/children" allowedMethods="GET" >
			<http:response statusCode="#[vars.httpStatus default 200]" />
			<http:error-response statusCode="#[vars.httpStatus default 500]" >
				<http:body ><![CDATA[#[output application/json --- payload default error.description]]]></http:body>
			</http:error-response>
		</http:listener>
		<ee:transform doc:name="Transform Message">
            <ee:variables>
                <ee:set-variable variableName="categoryType">attributes.uriParams.'categoryType'</ee:set-variable>
                <ee:set-variable variableName="parentId">attributes.uriParams.'parentId'</ee:set-variable>
            </ee:variables>
        </ee:transform>
        <flow-ref doc:name="blackboard-token-subFlow" doc:id="0ddfaa61-48f4-4b15-b818-13535b5c34c0" name="accesstoken_Flow" target="blackboardToken"/>
		<blackboard:get-child-categories doc:name="Course Category - Get Child Categories" doc:id="c0641efd-f8d8-48ff-add0-b6a40fa089a7" config-ref="Blackboard_config" categoryType="#[vars.categoryType]" parentId="#[vars.parentId]" correlationId="#[correlationId]"/>
    
</flow>
    <flow name="get:\v1\courseRoles:blackboard-rest-api-config">
        <http:listener doc:name="Listener" doc:id="d6da56eb-9e64-42f1-b2ba-231b09c85e78" config-ref="HTTP_Listener_config" path="/v1/courseRoles" allowedMethods="GET" >
			<http:response statusCode="#[vars.httpStatus default 200]" />
			<http:error-response statusCode="#[vars.httpStatus default 500]" >
				<http:body ><![CDATA[#[output application/json --- payload default error.description]]]></http:body>
			</http:error-response>
		</http:listener>
		<flow-ref doc:name="blackboard-token-subFlow" doc:id="fcf52236-1ac1-425a-8ffa-c2cc94a22763" name="accesstoken_Flow" target="blackboardToken"/>
		<blackboard:get-course-roles doc:name="Roles - Get Course Roles" doc:id="b396476e-828b-4e7a-9726-edcc6c178c53" config-ref="Blackboard_config" correlationId="#[correlationId]"/>
    
</flow>
    <flow name="get:\v1\courseRoles\(roleId):blackboard-rest-api-config">
        <http:listener doc:name="Listener" doc:id="4d695cf3-7608-498e-a246-e0ff60b2255b" config-ref="HTTP_Listener_config" path="/v1/courseRoles/{roleId}" allowedMethods="GET" >
			<http:response statusCode="#[vars.httpStatus default 200]" />
			<http:error-response statusCode="#[vars.httpStatus default 500]" >
				<http:body ><![CDATA[#[output application/json --- payload default error.description]]]></http:body>
			</http:error-response>
		</http:listener>
		<ee:transform doc:name="Transform Message">
            <ee:variables>
                <ee:set-variable variableName="roleId">attributes.uriParams.'roleId'</ee:set-variable>
            </ee:variables>
        </ee:transform>
        <flow-ref doc:name="blackboard-token-subFlow" doc:id="3ff5104b-923c-4092-a3ca-4bc2c001ba24" name="accesstoken_Flow" target="blackboardToken"/>
		<blackboard:get-course-role doc:name="Roles - Get Course Role" doc:id="2805fb05-7005-4915-8a87-188f27b048d5" config-ref="Blackboard_config" roleId="#[vars.roleId]" correlationId="#[correlationId]"/>
    
</flow>
    <flow name="get:\v1\courses\(courseId)\children:blackboard-rest-api-config">
        <http:listener doc:name="Listener" doc:id="0c024973-8b7b-454a-9712-646fdd7e7fdd" config-ref="HTTP_Listener_config" path="/v1/courses/{courseId}/children" allowedMethods="GET" >
			<http:response statusCode="#[vars.httpStatus default 200]" />
			<http:error-response statusCode="#[vars.httpStatus default 500]" >
				<http:body ><![CDATA[#[output application/json --- payload default error.description]]]></http:body>
			</http:error-response>
		</http:listener>
		<ee:transform doc:name="Transform Message">
            <ee:variables>
                <ee:set-variable variableName="courseId">attributes.uriParams.'courseId'</ee:set-variable>
            </ee:variables>
        </ee:transform>
        <flow-ref doc:name="blackboard-token-subFlow" doc:id="3acbba0e-1b2a-466e-bc9f-8fee068eb150" name="accesstoken_Flow" target="blackboardToken"/>
		<blackboard:getcourse-children doc:name="Courses - Get Course Children" doc:id="a5342a2e-0e8d-4590-bc0e-79896a2f221f" config-ref="Blackboard_config" courseId="#[vars.courseId]" correlationId="#[correlationId]"/>
    
</flow>
    <flow name="get:\v1\courses\(courseId)\children\(childCourseId):blackboard-rest-api-config">
        <http:listener doc:name="Listener" doc:id="05d39244-dbac-4f34-a82d-7ebc02187032" config-ref="HTTP_Listener_config" path="/v1/courses/{courseId}/children/{childCourseId}" allowedMethods="GET" >
			<http:response statusCode="#[vars.httpStatus default 200]" />
			<http:error-response statusCode="#[vars.httpStatus default 500]" >
				<http:body ><![CDATA[#[output application/json --- payload default error.description]]]></http:body>
			</http:error-response>
		</http:listener>
		<ee:transform doc:name="Transform Message">
            <ee:variables>
                <ee:set-variable variableName="courseId">attributes.uriParams.'courseId'</ee:set-variable>
                <ee:set-variable variableName="childCourseId">attributes.uriParams.'childCourseId'</ee:set-variable>
            </ee:variables>
        </ee:transform>
        <flow-ref doc:name="blackboard-token-subFlow" doc:id="070c93e3-48af-4ec0-be9d-3b223f539edd" name="accesstoken_Flow" target="blackboardToken"/>
		<blackboard:get-course-child doc:name="Courses - Get Course Child" doc:id="ea6b413e-0770-48de-abfe-206be9524a4b" config-ref="Blackboard_config" courseId="#[vars.courseId]" childCourseId="#[vars.childCourseId]" correlationId="#[correlationId]"/>
    </flow>
    <flow name="get:\v1\courses\(courseId)\gradebook\categories:blackboard-rest-api-config">
        <http:listener doc:name="Listener" doc:id="d0a70977-3e8f-47d7-9283-cdbd74a6e681" config-ref="HTTP_Listener_config" path="/v1/courses/{courseId}/gradebook/categories" allowedMethods="GET" >
			<http:response statusCode="#[vars.httpStatus default 200]" />
			<http:error-response statusCode="#[vars.httpStatus default 500]" >
				<http:body ><![CDATA[#[output application/json --- payload default error.description]]]></http:body>
			</http:error-response>
		</http:listener>
		<ee:transform doc:name="Transform Message">
            <ee:variables>
                <ee:set-variable variableName="courseId">attributes.uriParams.'courseId'</ee:set-variable>
            </ee:variables>
        </ee:transform>
        <flow-ref doc:name="blackboard-token-subFlow" doc:id="6f2fa8ba-b055-4e4e-8882-43648227df94" name="accesstoken_Flow" target="blackboardToken"/>
		<blackboard:get-gradebook-categories doc:name="Course Gradebook - Get Gradebook Categories" doc:id="5589d2fa-56b0-4050-824f-948be6c86f9a" config-ref="Blackboard_config" courseId="#[vars.courseId]" correlationId="#[correlationId]"/>
    </flow>
    <flow name="get:\v1\courses\(courseId)\meetings:blackboard-rest-api-config">
        <http:listener doc:name="Listener" doc:id="bbb26797-e757-40fe-a505-6c18ec003388" config-ref="HTTP_Listener_config" path="/v1/courses/{courseId}/meetings" allowedMethods="GET" >
			<http:response statusCode="#[vars.httpStatus default 200]" />
			<http:error-response statusCode="#[vars.httpStatus default 500]" >
				<http:body ><![CDATA[#[output application/json --- payload default error.description]]]></http:body>
			</http:error-response>
		</http:listener>
		<ee:transform doc:name="Transform Message">
            <ee:variables>
                <ee:set-variable variableName="courseId">attributes.uriParams.'courseId'</ee:set-variable>
            </ee:variables>
        </ee:transform>
        <flow-ref doc:name="blackboard-token-subFlow" doc:id="adc625e0-8f78-4ade-947f-6cc9dbed7b4f" name="accesstoken_Flow" target="blackboardToken"/>
		<blackboard:get-course-meeting doc:name="Attendance - Get Course Meeting" doc:id="f2230bba-50c5-44ff-b4de-12a6bae0395d" config-ref="Blackboard_config" courseId="#[vars.courseId]" correlationId="#[correlationId]"/>
    </flow>
    <flow name="get:\v1\courses\(courseId)\meetings\users\(userId):blackboard-rest-api-config">
        <http:listener doc:name="Listener" doc:id="95630498-c44a-4009-95ac-061ea87cb892" config-ref="HTTP_Listener_config" path="/v1/courses/{courseId}/meetings/users/{userId}" allowedMethods="GET" >
			<http:response statusCode="#[vars.httpStatus default 200]" />
			<http:error-response statusCode="#[vars.httpStatus default 500]" >
				<http:body ><![CDATA[#[output application/json --- payload default error.description]]]></http:body>
			</http:error-response>
		</http:listener>
		<ee:transform doc:name="Transform Message">
            <ee:variables>
                <ee:set-variable variableName="courseId">attributes.uriParams.'courseId'</ee:set-variable>
                <ee:set-variable variableName="userId">attributes.uriParams.'userId'</ee:set-variable>
            </ee:variables>
        </ee:transform>
        <flow-ref doc:name="blackboard-token-subFlow" doc:id="28386f24-b753-4b02-8516-3e5caadcb8e4" name="accesstoken_Flow" target="blackboardToken"/>
		<blackboard:get-attendance-by-user-id doc:name="Attendance - Get Attendance by User Id" doc:id="80d39840-0c3c-47d7-af44-7caf37cb5d91" config-ref="Blackboard_config" courseId="#[vars.courseId]" userId="#[vars.userId]" correlationId="#[correlationId]"/>
    </flow>
    <flow name="get:\v1\courses\(courseId)\meetings\(meetingId)\users:blackboard-rest-api-config">
        <http:listener doc:name="Listener" doc:id="7beaea58-66d8-47ac-8a81-8cb6c6212790" config-ref="HTTP_Listener_config" path="/v1/courses/{courseId}/meetings/{meetingId}/users" allowedMethods="GET" >
			<http:response statusCode="#[vars.httpStatus default 200]" />
			<http:error-response statusCode="#[vars.httpStatus default 500]" >
				<http:body ><![CDATA[#[output application/json --- payload default error.description]]]></http:body>
			</http:error-response>
		</http:listener>
		<ee:transform doc:name="Transform Message">
            <ee:variables>
                <ee:set-variable variableName="courseId">attributes.uriParams.'courseId'</ee:set-variable>
                <ee:set-variable variableName="meetingId">attributes.uriParams.'meetingId'</ee:set-variable>
            </ee:variables>
        </ee:transform>
        <flow-ref doc:name="blackboard-token-subFlow" doc:id="cf7b03e7-b6e7-484b-a826-b520e7209744" name="accesstoken_Flow" target="blackboardToken"/>
		<blackboard:get-attendance-recordsby-meeting-id doc:name="Attendance - Get Attendance Records by Meeting Id" doc:id="0ad5fd58-9468-4ef6-9cdc-25c610303255" config-ref="Blackboard_config" courseId="#[vars.courseId]" meetingId="#[vars.meetingId]" correlationId="#[correlationId]"/>
    </flow>
    <flow name="get:\v1\courses\(courseId)\meetings\(meetingId)\users\(userId):blackboard-rest-api-config">
        <http:listener doc:name="Listener" doc:id="4611ed4b-80dd-4397-9872-1232da029c81" config-ref="HTTP_Listener_config" path="/v1/courses/{courseId}/meetings/{meetingId}/users" allowedMethods="GET" >
			<http:response statusCode="#[vars.httpStatus default 200]" />
			<http:error-response statusCode="#[vars.httpStatus default 500]" >
				<http:body ><![CDATA[#[output application/json --- payload default error.description]]]></http:body>
			</http:error-response>
		</http:listener>
		<ee:transform doc:name="Transform Message">
            <ee:variables>
                <ee:set-variable variableName="courseId">attributes.uriParams.'courseId'</ee:set-variable>
                <ee:set-variable variableName="meetingId">attributes.uriParams.'meetingId'</ee:set-variable>
                <ee:set-variable variableName="userId">attributes.uriParams.'userId'</ee:set-variable>
            </ee:variables>
        </ee:transform>
        <flow-ref doc:name="blackboard-token-subFlow" doc:id="118cb16b-ba2b-4e55-9d96-11b2a06f53a1" name="accesstoken_Flow" target="blackboardToken"/>
		<blackboard:get-attendance-record doc:name="Attendance - Get Attendance Record" doc:id="343abd38-755b-4f40-b9bd-06a846a02a7a" config-ref="Blackboard_config" courseId="#[vars.courseId]" meetingId="#[vars.meetingId]" userId="#[vars.userId]" correlationId="#[correlationId]"/>
    </flow>
    <flow name="get:\v1\courses\(courseId)\users:blackboard-rest-api-config">
        <http:listener doc:name="Listener" doc:id="6fa379ec-bc65-4309-abb9-1085cb506887" config-ref="HTTP_Listener_config" path="/v1/courses/{courseId}/users" allowedMethods="GET" >
			<http:response statusCode="#[vars.httpStatus default 200]" />
			<http:error-response statusCode="#[vars.httpStatus default 500]" >
				<http:body ><![CDATA[#[output application/json --- payload default error.description]]]></http:body>
			</http:error-response>
		</http:listener>
		<ee:transform doc:name="Transform Message">
            <ee:variables>
                <ee:set-variable variableName="courseId">attributes.uriParams.'courseId'</ee:set-variable>
            </ee:variables>
        </ee:transform>
        <flow-ref doc:name="blackboard-token-subFlow" doc:id="e1d81b89-934b-479b-a51e-d1738f7b7bb2" name="accesstoken_Flow" target="blackboardToken"/>
		<blackboard:get-course-memberships doc:name="Course Membership - Get Course Memberships" doc:id="8a67bafb-882e-4ba4-b98c-aea69173e0c8" config-ref="Blackboard_config" courseId="#[vars.courseId]"/>
    </flow>
    <flow name="get:\v1\courses\(courseId)\users\(userId):blackboard-rest-api-config">
        <http:listener doc:name="Listener" doc:id="192cf561-2439-4f17-bc67-2b4ec09057cc" config-ref="HTTP_Listener_config" path="/v1/courses/{courseId}/users/{userId}" allowedMethods="GET" >
			<http:response statusCode="#[vars.httpStatus default 200]" />
			<http:error-response statusCode="#[vars.httpStatus default 500]" >
				<http:body ><![CDATA[#[output application/json --- payload default error.description]]]></http:body>
			</http:error-response>
		</http:listener>
		<ee:transform doc:name="Transform Message">
            <ee:variables>
                <ee:set-variable variableName="courseId">attributes.uriParams.'courseId'</ee:set-variable>
                <ee:set-variable variableName="userId">attributes.uriParams.'userId'</ee:set-variable>
            </ee:variables>
        </ee:transform>
        <flow-ref doc:name="blackboard-token-subFlow" doc:id="9bec45c0-4b8f-4b90-a5b3-1ff7673ea59e" name="accesstoken_Flow" target="blackboardToken"/>
		<blackboard:get-course-membership doc:name="Course Membership - Get Course Membership" doc:id="d5ee1c96-96f4-4b05-9603-03a99ee09d35" config-ref="Blackboard_config" courseId="#[vars.courseId]" userId="#[vars.userId]" correlationId="#[correlationId]"/>
    </flow>
    <flow name="get:\v1\institutionRoles:blackboard-rest-api-config">
        <http:listener doc:name="Listener" doc:id="78e892b3-5fb5-41a0-b263-e7bb855373cd" config-ref="HTTP_Listener_config" path="/v1/institutionRoles" allowedMethods="GET" >
			<http:response statusCode="#[vars.httpStatus default 200]" />
			<http:error-response statusCode="#[vars.httpStatus default 500]" >
				<http:body ><![CDATA[#[output application/json --- payload default error.description]]]></http:body>
			</http:error-response>
		</http:listener>
		<flow-ref doc:name="blackboard-token-subFlow" doc:id="61f06e09-c76b-4fa7-a839-fbc5899f07d8" name="accesstoken_Flow" target="blackboardToken"/>
		<blackboard:get-institution-roles doc:name="Roles - Get Institution Roles" doc:id="98b2d731-12a7-46c0-bdac-12252ea74885" config-ref="Blackboard_config" correlationId="#[correlationId]"/>
    </flow>
    <flow name="get:\v1\institutionRoles\(roleId):blackboard-rest-api-config">
        <http:listener doc:name="Listener" doc:id="0d6f24e8-c53d-49e3-bc3e-498492fd1993" config-ref="HTTP_Listener_config" path="/v1/institutionRoles/{roleId}" allowedMethods="GET" >
			<http:response statusCode="#[vars.httpStatus default 200]" />
			<http:error-response statusCode="#[vars.httpStatus default 500]" >
				<http:body ><![CDATA[#[output application/json --- payload default error.description]]]></http:body>
			</http:error-response>
		</http:listener>
		<ee:transform doc:name="Transform Message">
            <ee:variables>
                <ee:set-variable variableName="roleId">attributes.uriParams.'roleId'</ee:set-variable>
            </ee:variables>
        </ee:transform>
        <flow-ref doc:name="blackboard-token-subFlow" doc:id="0aaacb38-7d21-4f28-b475-da44d40599e6" name="accesstoken_Flow" target="blackboardToken"/>
		<blackboard:get-institution-role doc:name="Roles - Get Institution Role" doc:id="5fc62690-f115-4964-9325-3faee1d055a4" config-ref="Blackboard_config" roleId="#[vars.roleId]" correlationId="#[correlationId]"/>
    </flow>
    <flow name="get:\v1\terms:blackboard-rest-api-config">
        <http:listener doc:name="Listener" doc:id="4b0367fa-4137-4a3b-8051-979522ed1501" config-ref="HTTP_Listener_config" path="/v1/terms" allowedMethods="GET" >
			<http:response statusCode="#[vars.httpStatus default 200]" />
			<http:error-response statusCode="#[vars.httpStatus default 500]" >
				<http:body ><![CDATA[#[output application/json --- payload default error.description]]]></http:body>
			</http:error-response>
		</http:listener>
		<flow-ref doc:name="blackboard-token-subFlow" doc:id="94d43dfd-af64-4dc9-8575-a76845d5ce8c" name="accesstoken_Flow" target="blackboardToken"/>
		<blackboard:get-terms doc:name="Terms - Get Terms" doc:id="501a9fad-740b-4404-98cb-dc5b875b559e" config-ref="Blackboard_config" correlationId="#[correlationId]"/>
    </flow>
    <flow name="get:\v1\terms\(termId):blackboard-rest-api-config">
        <http:listener doc:name="Listener" doc:id="40783e5b-97e1-47cb-9afe-9e758fb10dca" config-ref="HTTP_Listener_config" path="/v1/terms/{termId}" allowedMethods="GET" >
			<http:response statusCode="#[vars.httpStatus default 200]" />
			<http:error-response statusCode="#[vars.httpStatus default 500]" >
				<http:body ><![CDATA[#[output application/json --- payload default error.description]]]></http:body>
			</http:error-response>
		</http:listener>
		<ee:transform doc:name="Transform Message">
            <ee:variables>
                <ee:set-variable variableName="termId">attributes.uriParams.'termId'</ee:set-variable>
            </ee:variables>
        </ee:transform>
        <flow-ref doc:name="blackboard-token-subFlow" doc:id="afa492de-5884-404b-bc0c-cf1dfa0702fa" name="accesstoken_Flow" target="blackboardToken"/>
		<blackboard:get-term doc:name="Terms - Get Term" doc:id="bbde300b-c2bc-424d-9668-292f4dd40fdf" config-ref="Blackboard_config" termId="#[vars.termId]" correlationId="#[correlationId]"/>
    </flow>
    <flow name="get:\v1\users:blackboard-rest-api-config">
        <http:listener doc:name="Listener" doc:id="dacf59a4-f45e-40db-9715-605c5cfd4e8e" config-ref="HTTP_Listener_config" path="/v1/users" allowedMethods="GET" >
			<http:response statusCode="#[vars.httpStatus default 200]" />
			<http:error-response statusCode="#[vars.httpStatus default 500]" >
				<http:body ><![CDATA[#[output application/json --- payload default error.description]]]></http:body>
			</http:error-response>
		</http:listener>
		<flow-ref doc:name="blackboard-token-subFlow" doc:id="c784cbc5-71ac-47e2-b2a4-87cc40ec0b1d" name="accesstoken_Flow" target="blackboardToken"/>
		<blackboard:get-users doc:name="Users - Get Users" doc:id="87316201-10b8-47ac-a3ca-e5f4c0738f3d" config-ref="Blackboard_config" correlationId="#[correlationId]"/>
    </flow>
    <flow name="get:\v1\users\(userId):blackboard-rest-api-config">
        <http:listener doc:name="Listener" doc:id="b8793274-2129-4d4e-a7c0-63eb4df98880" config-ref="HTTP_Listener_config" path="/v1/users/{userId}" allowedMethods="GET" >
			<http:response statusCode="#[vars.httpStatus default 200]" />
			<http:error-response statusCode="#[vars.httpStatus default 500]" >
				<http:body ><![CDATA[#[output application/json --- payload default error.description]]]></http:body>
			</http:error-response>
		</http:listener>
		<ee:transform doc:name="Transform Message">
            <ee:variables>
                <ee:set-variable variableName="userId">attributes.uriParams.'userId'</ee:set-variable>
            </ee:variables>
        </ee:transform>
        <flow-ref doc:name="blackboard-token-subFlow" doc:id="d84a6828-ba96-4a8d-ad0d-d2830ac00922" name="accesstoken_Flow" target="blackboardToken"/>
		<blackboard:get-user doc:name="Users - Get User" doc:id="e1127f48-6f08-4542-8407-3b72344e92f9" config-ref="Blackboard_config" userId="#[vars.userId]" correlationId="#[correlationId]"/>
    </flow>
    <flow name="get:\v1\users\(userId)\courses:blackboard-rest-api-config">
        <http:listener doc:name="Listener" doc:id="aa79fe41-b2dd-4a4f-9bb9-fb892c68ffe9" config-ref="HTTP_Listener_config" path="/v1/users/{userId}/courses" allowedMethods="GET" >
			<http:response statusCode="#[vars.httpStatus default 200]" />
			<http:error-response statusCode="#[vars.httpStatus default 500]" >
				<http:body ><![CDATA[#[output application/json --- payload default error.description]]]></http:body>
			</http:error-response>
		</http:listener>
		<ee:transform doc:name="Transform Message">
            <ee:variables>
                <ee:set-variable variableName="userId">attributes.uriParams.'userId'</ee:set-variable>
            </ee:variables>
        </ee:transform>
        <flow-ref doc:name="blackboard-token-subFlow" doc:id="50e25299-83cf-4921-9483-4cfbaaea545f" name="accesstoken_Flow" target="blackboardToken"/>
		<blackboard:get-user-memberships doc:name="Course Membership - Get User Memberships" doc:id="704f2cd1-b3ff-4d10-ae5d-ff8fb00e804f" config-ref="Blackboard_config" userId="#[vars.userId]"/>
    </flow>
    <flow name="get:\v2\courses\(courseId)\gradebook\columns:blackboard-rest-api-config">
        <http:listener doc:name="Listener" doc:id="6ac18e8c-3b26-4dc9-8bc1-4ba94e51f7db" config-ref="HTTP_Listener_config" path="/v2/courses/{courseId}/gradebook/columns" allowedMethods="GET" >
			<http:response statusCode="#[vars.httpStatus default 200]" />
			<http:error-response statusCode="#[vars.httpStatus default 500]" >
				<http:body ><![CDATA[#[output application/json --- payload default error.description]]]></http:body>
			</http:error-response>
		</http:listener>
		<ee:transform doc:name="Transform Message">
            <ee:variables>
                <ee:set-variable variableName="courseId">attributes.uriParams.'courseId'</ee:set-variable>
            </ee:variables>
        </ee:transform>
        <flow-ref doc:name="blackboard-token-subFlow" doc:id="8491b8fb-f08b-4dc8-ae0e-bd4d302ddeee" name="accesstoken_Flow" target="blackboardToken"/>
		<blackboard:get-grade-columns doc:name="Course Gradebook - Get Grade Columns" doc:id="730378b5-5d23-40a4-8c16-66c0c5fcbc93" config-ref="Blackboard_config" courseId="#[vars.courseId]"/>
    </flow>
    <flow name="get:\v2\courses\(courseId)\gradebook\columns\(columnId):blackboard-rest-api-config">
        <http:listener doc:name="Listener" doc:id="e6718f1e-fe78-4f27-9335-485a3c51a77e" config-ref="HTTP_Listener_config" path="/v2/courses/{courseId}/gradebook/columns/{columnId}" allowedMethods="GET" >
			<http:response statusCode="#[vars.httpStatus default 200]" />
			<http:error-response statusCode="#[vars.httpStatus default 500]" >
				<http:body ><![CDATA[#[output application/json --- payload default error.description]]]></http:body>
			</http:error-response>
		</http:listener>
		<ee:transform doc:name="Transform Message">
            <ee:variables>
                <ee:set-variable variableName="courseId">attributes.uriParams.'courseId'</ee:set-variable>
                <ee:set-variable variableName="columnId">attributes.uriParams.'columnId'</ee:set-variable>
            </ee:variables>
        </ee:transform>
        <flow-ref doc:name="blackboard-token-subFlow" doc:id="cadf6e08-a66d-46d3-9034-a3d815a4c3fd" name="accesstoken_Flow" target="blackboardToken"/>
		<blackboard:get-grade-column doc:name="Course Gradebook - Get Grade Column" doc:id="fd905387-ee12-4e7b-9286-54036ed0e47c" config-ref="Blackboard_config" courseId="#[vars.courseId]" columnId="#[vars.columnId]" correlationId="#[correlationId]"/>
    </flow>
    <flow name="get:\v2\courses\(courseId)\gradebook\columns\(columnId)\users:blackboard-rest-api-config">
        <http:listener doc:name="Listener" doc:id="f968bad3-13fa-4e7a-b441-fef6163ea2b7" config-ref="HTTP_Listener_config" path="/v2/courses/{courseId}/gradebook/columns/{columnId}/users" allowedMethods="GET" >
			<http:response statusCode="#[vars.httpStatus default 200]" />
			<http:error-response statusCode="#[vars.httpStatus default 500]" >
				<http:body ><![CDATA[#[output application/json --- payload default error.description]]]></http:body>
			</http:error-response>
		</http:listener>
		<ee:transform doc:name="Transform Message">
            <ee:variables>
                <ee:set-variable variableName="courseId">attributes.uriParams.'courseId'</ee:set-variable>
                <ee:set-variable variableName="columnId">attributes.uriParams.'columnId'</ee:set-variable>
            </ee:variables>
        </ee:transform>
        <flow-ref doc:name="blackboard-token-subFlow" doc:id="77922417-d8bc-440f-8e22-45f35f27aeb0" name="accesstoken_Flow" target="blackboardToken"/>
		<blackboard:get-column-grades doc:name="Course Gradebook - Get Column Grades" doc:id="e3a4ea94-7bdc-4967-b8a2-c926fafd7a0a" config-ref="Blackboard_config" courseId="#[vars.courseId]" columnId="#[vars.columnId]"/>
    </flow>
    <flow name="get:\v2\courses\(courseId)\gradebook\columns\(columnId)\users\(userId):blackboard-rest-api-config">
        <http:listener doc:name="Listener" doc:id="94312961-d094-4f87-8c2e-0b4177509240" config-ref="HTTP_Listener_config" path="/v2/courses/{courseId}/gradebook/columns/{columnId}/users/{userId}" allowedMethods="GET" >
			<http:response statusCode="#[vars.httpStatus default 200]" />
			<http:error-response statusCode="#[vars.httpStatus default 500]" >
				<http:body ><![CDATA[#[output application/json --- payload default error.description]]]></http:body>
			</http:error-response>
		</http:listener>
		<ee:transform doc:name="Transform Message">
            <ee:variables>
                <ee:set-variable variableName="courseId">attributes.uriParams.'courseId'</ee:set-variable>
                <ee:set-variable variableName="columnId">attributes.uriParams.'columnId'</ee:set-variable>
                <ee:set-variable variableName="userId">attributes.uriParams.'userId'</ee:set-variable>
            </ee:variables>
        </ee:transform>
        <flow-ref doc:name="blackboard-token-subFlow" doc:id="4b924d08-ba60-48c4-9b32-ff607cd29101" name="accesstoken_Flow" target="blackboardToken"/>
		<blackboard:get-column-grade doc:name="Course Gradebook - Get Column Grade" doc:id="79cf87f9-cceb-40bd-8ae0-ba3fcdc06199" config-ref="Blackboard_config" courseId="#[vars.courseId]" columnId="#[vars.columnId]" userId="#[vars.userId]" correlationId="#[correlationId]"/>
    </flow>
    <flow name="get:\v2\courses\(courseId)\gradebook\users\(userId):blackboard-rest-api-config">
        <http:listener doc:name="Listener" doc:id="e7dd76b2-095e-4224-83aa-7d5eb8340f78" config-ref="HTTP_Listener_config" path="/v2/courses/{courseId}/gradebook/users/{userId}" allowedMethods="GET" >
			<http:response statusCode="#[vars.httpStatus default 200]" />
			<http:error-response statusCode="#[vars.httpStatus default 500]" >
				<http:body ><![CDATA[#[output application/json --- payload default error.description]]]></http:body>
			</http:error-response>
		</http:listener>
		<ee:transform doc:name="Transform Message">
            <ee:variables>
                <ee:set-variable variableName="courseId">attributes.uriParams.'courseId'</ee:set-variable>
                <ee:set-variable variableName="userId">attributes.uriParams.'userId'</ee:set-variable>
            </ee:variables>
        </ee:transform>
        <flow-ref doc:name="blackboard-token-subFlow" doc:id="22591549-2d36-4985-95ac-2b842ab673de" name="accesstoken_Flow" target="blackboardToken"/>
		<blackboard:get-user-grades doc:name="Course Gradebook - Get User Grades" doc:id="f572cd56-a517-4471-9b80-bcfdbcea68ae" config-ref="Blackboard_config" courseId="#[vars.courseId]" userId="#[vars.userId]"/>
    </flow>
    <flow name="get:\v3\courses:blackboard-rest-api-config">
        <http:listener doc:name="Listener" doc:id="32701bd6-51e1-4f23-8967-7e5944b32738" config-ref="HTTP_Listener_config" path="/v3/courses" allowedMethods="GET" >
			<http:response statusCode="#[vars.httpStatus default 200]" />
			<http:error-response statusCode="#[vars.httpStatus default 500]" >
				<http:body ><![CDATA[#[output application/json --- payload default error.description]]]></http:body>
			</http:error-response>
		</http:listener>
		<flow-ref doc:name="blackboard-token-subFlow" doc:id="b96a22f2-1e27-428a-b855-ac49bd7196f3" name="accesstoken_Flow" target="blackboardToken"/>
		<blackboard:get-courses doc:name="Courses - Get Courses" doc:id="43db6a0c-ee30-437e-a28c-45e06f440229" config-ref="Blackboard_config" correlationId="#[correlationId]"/>
    
</flow>
    <flow name="get:\v3\courses\(courseId):blackboard-rest-api-config">
        <http:listener doc:name="Listener" doc:id="2e308275-1acf-4eb4-8d9f-77386675a948" config-ref="HTTP_Listener_config" path="/v3/courses/{courseId}" allowedMethods="GET" >
			<http:response statusCode="#[vars.httpStatus default 200]" />
			<http:error-response statusCode="#[vars.httpStatus default 500]" >
				<http:body ><![CDATA[#[output application/json --- payload default error.description]]]></http:body>
			</http:error-response>
		</http:listener>
		<ee:transform doc:name="Transform Message">
            <ee:variables>
                <ee:set-variable variableName="courseId">attributes.uriParams.'courseId'</ee:set-variable>
            </ee:variables>
        </ee:transform>
        <flow-ref doc:name="blackboard-token-subFlow" doc:id="9963bca7-b3f4-4d32-88e1-d052599ef3d0" name="accesstoken_Flow" target="blackboardToken"/>
		<blackboard:get-course doc:name="Courses - Get Course" doc:id="de65660e-05c6-48c0-82a7-5938832b4d9f" config-ref="Blackboard_config" courseId="#[vars.courseId]" correlationId="#[correlationId]"/>
    </flow>
    <flow name="post:\oauth2\token:application\x-www-form-urlencoded:blackboard-rest-api-config">
        <ee:transform doc:name="Transform Message">
            <ee:message>
                <ee:set-payload><![CDATA[%dw 2.0
output application/json
---
{
  access_token: "abc123tokenexample",
  token_type: "bearer",
  expires_in: 3600,
  scope: "read write delete"
} as Object {encoding: "UTF-8", mediaType: "application/json"}]]></ee:set-payload>
            </ee:message>
        </ee:transform>
    </flow>
    <flow name="post:\v1\catalog\categories\(categoryType):application\json:blackboard-rest-api-config">
        <http:listener doc:name="Listener" doc:id="e67e52a6-74e4-4f8d-a1d9-290be56646b0" config-ref="HTTP_Listener_config" path="/v1/catalog/categories/{categoryType}" allowedMethods="POST" >
			<http:response statusCode="#[vars.httpStatus default 200]" />
			<http:error-response statusCode="#[vars.httpStatus default 500]" >
				<http:body ><![CDATA[#[output application/json --- payload default error.description]]]></http:body>
			</http:error-response>
		</http:listener>
		<ee:transform doc:name="Transform Message">
            <ee:variables>
                <ee:set-variable variableName="categoryType">attributes.uriParams.'categoryType'</ee:set-variable>
            </ee:variables>
        </ee:transform>
        <flow-ref doc:name="blackboard-token-subFlow" doc:id="cbae845a-5f85-48f7-8823-e7453aa43c03" name="accesstoken_Flow" target="blackboardToken"/>
		<blackboard:create-category doc:name="Course Category - Create Category" doc:id="c5fce548-de35-4f88-b64e-39dc93f8c3b5" config-ref="Blackboard_config" categoryType="#[vars.categoryType]" correlationId="#[correlationId]">
			<blackboard:course_category_-_create_category--body ><![CDATA[#[payload]]]></blackboard:course_category_-_create_category--body>
		</blackboard:create-category>
    </flow>
    <flow name="post:\v1\courses\(courseId)\meetings\(meetingId)\users:application\json:blackboard-rest-api-config">
        <http:listener doc:name="Listener" doc:id="a43c1753-d524-4efa-b3c4-2d9c380a3084" config-ref="HTTP_Listener_config" path="/v1/courses/{courseId}/meetings/{meetingId}/users" allowedMethods="POST" >
			<http:response statusCode="#[vars.httpStatus default 200]" />
			<http:error-response statusCode="#[vars.httpStatus default 500]" >
				<http:body ><![CDATA[#[output application/json --- payload default error.description]]]></http:body>
			</http:error-response>
		</http:listener>
		<ee:transform doc:name="Transform Message">
            <ee:variables>
                <ee:set-variable variableName="courseId">attributes.uriParams.'courseId'</ee:set-variable>
                <ee:set-variable variableName="meetingId">attributes.uriParams.'meetingId'</ee:set-variable>
            </ee:variables>
        </ee:transform>
        <flow-ref doc:name="blackboard-token-subFlow" doc:id="7952c40d-f78b-4510-806a-665fe5f687dc" name="accesstoken_Flow" target="blackboardToken"/>
		<blackboard:create-attendance-record doc:name="Attendance - Create Attendance Record" doc:id="6d46df21-38cb-48cd-b49f-65d9afcb1486" config-ref="Blackboard_config" courseId="#[vars.courseId]" meetingId="#[vars.meetingId]" correlationId="#[correlationId]">
			<blackboard:attendance_-_create_attendance_record--body ><![CDATA[#[payload]]]></blackboard:attendance_-_create_attendance_record--body>
		</blackboard:create-attendance-record>
    </flow>
    <flow name="post:\v1\courses\(courseId)\meetings:application\json:blackboard-rest-api-config">
        <http:listener doc:name="Listener" doc:id="415e0892-2ef7-4e94-8b6e-c6c45a118b36" config-ref="HTTP_Listener_config" path="/v1/courses/{courseId}/meetings" allowedMethods="POST" >
			<http:response statusCode="#[vars.httpStatus default 200]" />
			<http:error-response statusCode="#[vars.httpStatus default 500]" >
				<http:body ><![CDATA[#[output application/json --- payload default error.description]]]></http:body>
			</http:error-response>
		</http:listener>
		<ee:transform doc:name="Transform Message">
            <ee:variables>
                <ee:set-variable variableName="courseId">attributes.uriParams.'courseId'</ee:set-variable>
            </ee:variables>
        </ee:transform>
        <flow-ref doc:name="blackboard-token-subFlow" doc:id="be904812-36c3-42f2-99aa-258292fd16a5" name="accesstoken_Flow" target="blackboardToken"/>
		<blackboard:create-course-meeting doc:name="Attendance - Create Course Meeting" doc:id="0ad7e349-dd30-43ac-8371-b00d717b64d8" config-ref="Blackboard_config" courseId="#[vars.courseId]" correlationId="#[correlationId]">
			<blackboard:attendance_-_create_course_meeting--body ><![CDATA[#[payload]]]></blackboard:attendance_-_create_course_meeting--body>
		</blackboard:create-course-meeting>
    </flow>
    <flow name="post:\v1\terms:application\json:blackboard-rest-api-config">
        <http:listener doc:name="Listener" doc:id="c3bc1b40-3fb1-4fb8-9df4-b064b01b5b0e" config-ref="HTTP_Listener_config" path="/v1/terms" allowedMethods="POST" >
			<http:response statusCode="#[vars.httpStatus default 200]" />
			<http:error-response statusCode="#[vars.httpStatus default 500]" >
				<http:body ><![CDATA[#[output application/json --- payload default error.description]]]></http:body>
			</http:error-response>
		</http:listener>
		<flow-ref doc:name="blackboard-token-subFlow" doc:id="49712df4-4aa8-4523-8b87-0aaaf15a70ff" name="accesstoken_Flow" target="blackboardToken"/>
		<blackboard:create-term doc:name="Terms - Create Term" doc:id="428e11fc-039f-4476-8b8e-3b95348e92cf" config-ref="Blackboard_config" correlationId="#[correlationId]">
			<blackboard:terms_-_create_term--body ><![CDATA[#[payload]]]></blackboard:terms_-_create_term--body>
		</blackboard:create-term>
    </flow>
    <flow name="post:\v1\users:application\json:blackboard-rest-api-config">
        <http:listener doc:name="Listener" doc:id="a16d9c60-2eae-444f-8113-f6db0c39c136" config-ref="HTTP_Listener_config" path="/v1/users" allowedMethods="POST" >
			<http:response statusCode="#[vars.httpStatus default 200]" />
			<http:error-response statusCode="#[vars.httpStatus default 500]" >
				<http:body ><![CDATA[#[output application/json --- payload default error.description]]]></http:body>
			</http:error-response>
		</http:listener>
		<flow-ref doc:name="blackboard-token-subFlow" doc:id="b3accaf5-e422-4877-8b94-4fb8fd367eb3" name="accesstoken_Flow" target="blackboardToken"/>
		<blackboard:create-user doc:name="Users - Create User" doc:id="c0efc5a6-48be-45cb-b5fd-5ca7ce7bc295" config-ref="Blackboard_config" correlationId="#[correlationId]">
			<blackboard:users_-_create_user--body ><![CDATA[#[payload]]]></blackboard:users_-_create_user--body>
		</blackboard:create-user>
    </flow>
    <flow name="post:\v3\courses:application\json:blackboard-rest-api-config">
        <http:listener doc:name="Listener" doc:id="acc5d410-d0ad-4497-b8b2-10b8165ef16d" config-ref="HTTP_Listener_config" path="/v3/courses" allowedMethods="POST" >
			<http:response statusCode="#[vars.httpStatus default 200]" />
			<http:error-response statusCode="#[vars.httpStatus default 500]" >
				<http:body ><![CDATA[#[output application/json --- payload default error.description]]]></http:body>
			</http:error-response>
		</http:listener>
		<flow-ref doc:name="blackboard-token-subFlow" doc:id="122ee0ff-e563-499d-95cf-1ab801ae9c31" name="accesstoken_Flow" target="blackboardToken"/>
        <blackboard:create-course doc:name="Courses - Create Course" doc:id="f311166d-edc2-4e9e-9e3b-cac717abb070" config-ref="Blackboard_config" correlationId="#[correlationId]">
			<blackboard:courses_-_create_course--body ><![CDATA[#[payload]]]></blackboard:courses_-_create_course--body>
		</blackboard:create-course>
		<logger level="INFO" doc:name="Logger" doc:id="0fe1e399-345b-4f80-a853-905d36fddb4f" />
    </flow>
    <flow name="patch:\v1\courses\(courseId)\meetings\(meetingId):application\json:blackboard-rest-api-config">
        <http:listener doc:name="Listener" doc:id="8da9b204-9c0e-4468-8799-0ce4141ce791" config-ref="HTTP_Listener_config" path="/v1/courses/{courseId}/meetings/{meetingId}" allowedMethods="PATCH" >
			<http:response statusCode="#[vars.httpStatus default 200]" />
			<http:error-response statusCode="#[vars.httpStatus default 500]" >
				<http:body ><![CDATA[#[output application/json --- payload default error.description]]]></http:body>
			</http:error-response>
		</http:listener>
		<ee:transform doc:name="Transform Message">
            <ee:variables>
                <ee:set-variable variableName="courseId">attributes.uriParams.'courseId'</ee:set-variable>
                <ee:set-variable variableName="meetingId">attributes.uriParams.'meetingId'</ee:set-variable>
            </ee:variables>
        </ee:transform>
        <flow-ref doc:name="blackboard-token-subFlow" doc:id="6519a84c-2de6-4ea3-b9e8-518f2c365f43" name="accesstoken_Flow" target="blackboardToken"/>
		<blackboard:update-course-meeting doc:name="Attendance - Update Course Meeting" doc:id="ece60e96-2989-404c-a4c9-7e1607ee0b51" config-ref="Blackboard_config" courseId="#[vars.courseId]" meetingId="#[vars.meetingId]" correlationId="#[correlationId]">
			<blackboard:attendance_-_update_course_meeting--body ><![CDATA[#[payload]]]></blackboard:attendance_-_update_course_meeting--body>
		</blackboard:update-course-meeting>
    </flow>
	
</mule>
